{"A6":{"ad_id":117,"name":null,"holc_grade":"A","sheets":1,"url":"//s3.amazonaws.com/holc/ads/OH/Dayton/1937/A6/{z}/{x}_{y}.png","areaDesc":{"1":{"1":"Van Buren Township, south of Oakwood.","2":"A","3":"6"},"2":"Hilly","3":"Large estates - best section around Dayton","4":"None","5":{"g":{"1":"Moderately","2":""},"f":"","e":"None","d":{"1":"None","2":""},"c":{"1":"None","2":""},"b":"10,000 up","a":"Professionals & Executives"},"6":{"d":"Good","c":"20 years.","b":"brick and stone","a":"Single family detached 8-14 rooms."},"7":{"1":"$25,000 - 80,000","2":"$30,000","3":"No rentals","4":"","5":"1933","6":"No Activity","7":"","8":"","9":"","10":"","11":"","12":"","13":"","14":"","15":"","16":"","17":"","18":"","19":"1929","20":"","21":"1929","22":""},"8":{"c":"100","b":"100","a":"50"},"9":{"c":"Good","b":"Single family detached $30,000","a":"Good"},"10":{"c":"- - - -","b":"- - - -","a":"None"},"11":{"b":"20-25","a":"Single family detached $30,000"},"12":{"b":"good","a":"good"},"13":"Upward","14":"Best green","15":{"1":"F.C. Devlin, Jr. Field Agent A. Lawson Jr. Field Agent, C.A. Fleming - Loan Service Representative","2":"February 25, 1937","3":""}}},"D13":{"ad_id":117,"name":null,"holc_grade":"D","sheets":1,"url":"//s3.amazonaws.com/holc/ads/OH/Dayton/1937/D13/{z}/{x}_{y}.png","areaDesc":{"1":{"1":"Dayton","2":"D","3":"12"},"2":"Low- Level","3":"Good transportation and schools.","4":"Old houses being converted into cheap rooming house section","5":{"g":{"1":"xxxxx","2":"xxxxx"},"f":"75%","e":"Foreigners","d":{"1":"Yes","2":"10"},"c":{"1":"Italian Hungarian","2":"20"},"b":"900","a":"Clerks-laborers"},"6":{"d":"Fair","c":"50 years","b":"Brick and Frame","a":"1 & 2 family detached apartments"},"7":{"1":"","2":"$3,000","3":"","4":"27","5":"1933","6":"","7":"1200","8":"40","9":"","10":"12","11":"44.4","12":"1937","13":"","14":"1800","15":"60","16":"","17":"17","18":"62.9","19":"1929","20":"","21":"1929","22":""},"8":{"c":"40","b":"95","a":"100"},"9":{"c":"","b":"","a":"None"},"10":{"c":"Fair","b":"Anything available $18.","a":"Fair"},"11":{"b":"","a":"None"},"12":{"b":"","a":"None"},"13":"Downward","14":"Low Red.","15":{"1":"F.C. Devlin, Jr., Field Agent, A. Lawson, Jr., Field Agent, C.A. Fleming - Loan Service Representative","2":"March 10, 1937","3":""}}},"C5":{"ad_id":117,"name":null,"holc_grade":"C","sheets":1,"url":"//s3.amazonaws.com/holc/ads/OH/Dayton/1937/C5/{z}/{x}_{y}.png","areaDesc":{"1":{"1":"Dayton","2":"C","3":"5"},"2":"Level","3":"Transportation and schools good; churches; all street improvements.","4":"None","5":{"g":{"1":"xxxxx","2":"xxxxx"},"f":"15%","e":"Better type of foreign","d":{"1":"None","2":""},"c":{"1":"Small percentage Better class","2":""},"b":"1,500","a":"Better class laborer-Clerks"},"6":{"d":"Fair","c":"40 years","b":"Frame","a":"1 & 2 family detached"},"7":{"1":"4,000 - 5,000","2":"4,500","3":"30 - 40","4":"35","5":"1933","6":"2,000 - 2,750","7":"2,200","8":"48.80%","9":"15 - 25","10":"20","11":"57.10%","12":"1937","13":"3,000 - 4,000","14":"3,200","15":"71.10%","16":"25 - 35","17":"30","18":"85.70%","19":"1929","20":"","21":"1929","22":""},"8":{"c":"50","b":"95","a":"100"},"9":{"c":"Poor","b":"","a":"Poor"},"10":{"c":"Good","b":"Single family house $30","a":"Good"},"11":{"b":"","a":"None"},"12":{"b":"","a":"Limited"},"13":"Downward","14":"Old type houses. Low yellow.","15":{"1":"F.C. Devlin, Jr., Field Agent, A. Lawson, Jr., Field Agent, C.A. Fleming, Loan Service Representative.","2":"March 5, 1937","3":""}}},"C2":{"ad_id":117,"name":null,"holc_grade":"C","sheets":1,"url":"//s3.amazonaws.com/holc/ads/OH/Dayton/1937/C2/{z}/{x}_{y}.png","areaDesc":{"1":{"1":"Dayton","2":"C","3":"2"},"2":"Level - high","3":"Good transportation; good schools; churches; playgrounds; good fire protection","4":"","5":{"g":{"1":"","2":"xxxxxx"},"f":"10%","e":"None","d":{"1":"No","2":""},"c":{"1":"None","2":""},"b":"1200","a":"Better class laborers - Clerks"},"6":{"d":"","c":"","b":"Frame","a":"5 & 6 room, 1 story; predominates single family detached"},"7":{"1":"$3,500 - 4,500","2":"$4,000","3":"25 - 35","4":"30","5":"1933","6":"1,800 - 2,750","7":"2,000","8":"50","9":"12 - 20","10":"15","11":"50","12":"1937","13":"3,000 - 3,500","14":"3,200","15":"80","16":"22 - 30","17":"26","18":"80.6","19":"1929","20":"","21":"1929","22":""},"8":{"c":"90","b":"100","a":"80"},"9":{"c":"Fair","b":"Single Family detached $2,800","a":"Fair"},"10":{"c":"Good","b":"Single family detached $26","a":"Good"},"11":{"b":"12","a":"Single family detached $3,200"},"12":{"b":"Ample","a":"Ample"},"13":"Upward","14":"Some \"jerry built houses\". Medium Yellow.","15":{"1":"F.C. Devlin, Jr. Field Agent, A.Lawson, Jr. Field Agent, C.A. Fleming, Loan Service Representative","2":"March 3, 1937","3":""}}},"D3":{"ad_id":117,"name":null,"holc_grade":"D","sheets":1,"url":"//s3.amazonaws.com/holc/ads/OH/Dayton/1937/D3/{z}/{x}_{y}.png","areaDesc":{"1":{"1":"Dayton","2":"Dayton","3":"3"},"2":"High-Rolling","3":"None","4":"Close to railroad tracks and industrial plants, bad odors, noisy.","5":{"g":{"1":"xxxxx","2":"xxxxx"},"f":"50%","e":"None","d":{"1":"None","2":""},"c":{"1":"None","2":""},"b":"900","a":"Laborer"},"6":{"d":"poor","c":"30 years","b":"Frame","a":"1 and 2 family detached"},"7":{"1":"","2":"$3,000","3":"","4":"$35","5":"1933","6":"","7":"1700","8":"56.6","9":"","10":"20","11":"57.1","12":"1937","13":"","14":"2400","15":"80","16":"","17":"25","18":"80","19":"1929","20":"","21":"1929","22":""},"8":{"c":"30","b":"100","a":"80"},"9":{"c":"poor","b":"1 family detached $2500","a":"Poor"},"10":{"c":"good","b":"1 family detached $25","a":"good"},"11":{"b":"","a":"None"},"12":{"b":"Limited","a":"Limited"},"13":"Downward","14":"Indications are that entire section will become industrial area. Low red.","15":{"1":"F.C. Devlin, Jr., Field Agent, A. Lawson, Jr., Field Agent, C.A. Fleming, Loan Service Representative","2":"March 9, 1937","3":""}}},"A7":{"ad_id":117,"name":null,"holc_grade":"A","sheets":1,"url":"//s3.amazonaws.com/holc/ads/OH/Dayton/1937/A7/{z}/{x}_{y}.png","areaDesc":{"1":{"1":"Dayten","2":"A","3":"7"},"2":"Rolling","3":"Highly restricted - partly wooded - high class residential good schools - playground - library - good transportation - city fire and police protection.","4":"None","5":{"g":{"1":"Moderately","2":""},"f":"None","e":"None","d":{"1":"None","2":""},"c":{"1":"None","2":""},"b":"4000","a":"Executives & professional"},"6":{"d":"Good","c":"15 years","b":"Good","a":"single family detached 7 to 9 rooms"},"7":{"1":"10,000 - 12,000","2":"11,000","3":"Few Rentals","4":"","5":"1933","6":"6,000 - 7,500","7":"6,800","8":"61.80%","9":"","10":"","11":"","12":"1937","13":"8,000 - 10,000","14":"9,000","15":"82%","16":"","17":"","18":"","19":"1929","20":"","21":"1929","22":""},"8":{"c":"95","b":"100","a":"50"},"9":{"c":"Fair","b":"single family detached 9,000","a":"Fair"},"10":{"c":"- - - -","b":"- - - -","a":"few rentals"},"11":{"b":"25 - 30","a":"$9,000 singles"},"12":{"b":"ample","a":"ample"},"13":"Upward","14":"The most exclusive residential section in Dayton (not including Oakwood) High Green.","15":{"1":"F.C. Devlin, Jr., Field Agent, A. Lawson, Jr., Field Agent, C.A. Fleming - Loan Service Representative.","2":"February 25, 1937","3":""}}},"C10":{"ad_id":117,"name":null,"holc_grade":"C","sheets":1,"url":"//s3.amazonaws.com/holc/ads/OH/Dayton/1937/C10/{z}/{x}_{y}.png","areaDesc":{"1":{"1":"Dayton","2":"C","3":"10"},"2":"Low","3":"Near business section and center of city, good schools, good transportation.","4":"None","5":{"g":{"1":"xxxxx","2":"xxxxx"},"f":"15%","e":"None","d":{"1":"None","2":""},"c":{"1":"None","2":""},"b":"1,500","a":"Laborers - Mechanics"},"6":{"d":"Fair","c":"35 years","b":"frame","a":"1 & 2 family detached"},"7":{"1":"4,500 - 5,500","2":"$5,000","3":"35 - 45","4":"$40","5":"1933","6":"2,000 - 3,000","7":"2,500","8":"50","9":"20 - 30","10":"25","11":"62.50%","12":"1937","13":"3,500 - 4,500","14":"4,000","15":"80","16":"30 - 40","17":"35","18":"87.50%","19":"1929","20":"","21":"1929","22":""},"8":{"c":"50","b":"100","a":"100"},"9":{"c":"Fair","b":"Single family detached $4,000","a":"Fair"},"10":{"c":"good","b":"Single family detached $35","a":"Good"},"11":{"b":"","a":"None"},"12":{"b":"Limited","a":"Limited"},"13":"Downward","14":"Medium yellow.","15":{"1":"F.C. Devlin, Jr., Field Agent, A. Lawson, Jr. Field Agent, C.A.Fleming, Loan Service Representative.","2":"March 5, 1937","3":""}}},"C6":{"ad_id":117,"name":null,"holc_grade":"C","sheets":1,"url":"//s3.amazonaws.com/holc/ads/OH/Dayton/1937/C6/{z}/{x}_{y}.png","areaDesc":{"1":{"1":"Dayton","2":"C","3":"6"},"2":"Level-high","3":"Good transportation; good schools; all street improvements","4":"All old property. No restrictions.","5":{"g":{"1":"xxxxx","2":"xxxxx"},"f":"50%","e":"Italian","d":{"1":"No","2":""},"c":{"1":"Italian","2":"30"},"b":"1,200","a":"Laborers mostly"},"6":{"d":"Fair","c":"40 years","b":"Frame","a":"1 & 2 family detached"},"7":{"1":"$3,000 - 4,000","2":"$3,500","3":"$20 - 30","4":"$25","5":"1933","6":"1,500 - 2,500","7":"1,800","8":"51.10%","9":"12 - 18","10":"14","11":"62.80%","12":"1937","13":"2,000 - 3,000","14":"2,200","15":"62.80%","16":"20 - 25","17":"22","18":"88","19":"1929","20":"","21":"1929","22":""},"8":{"c":"50","b":"100","a":"100"},"9":{"c":"","b":"","a":"None"},"10":{"c":"Good","b":"1 family $22","a":"Good"},"11":{"b":"","a":"None"},"12":{"b":"Limited","a":"Limited"},"13":"Downward","14":"Low yellow","15":{"1":"F.C. Devlin, Jr. Field Agent, A. Lawson, Jr. Field Agent, C.A. Fleming, Loan Service Representative","2":"March 5, 1937","3":""}}},"B4":{"ad_id":117,"name":null,"holc_grade":"B","sheets":1,"url":"//s3.amazonaws.com/holc/ads/OH/Dayton/1937/B4/{z}/{x}_{y}.png","areaDesc":{"1":{"1":"Dayton & Oakwood","2":"B","3":"4"},"2":"High level","3":"Highly restricted desirable residential section - close to N.C.R Plant - good transportation","4":"None","5":{"g":{"1":"moderately","2":""},"f":"None","e":"None","d":{"1":"None","2":""},"c":{"1":"None","2":""},"b":"3,500","a":"Jr. executives & upper class"},"6":{"d":"Good","c":"20 years","b":"Brick and frame","a":"Single family detached"},"7":{"1":"9,000 - 12,000","2":"$10,500","3":"60 - 75","4":"70","5":"1933","6":"5,000 - 6,500","7":"6,000","8":"57.14%","9":"30 - 45","10":"35","11":"50","12":"1937","13":"7,000 - 9,000","14":"8,000","15":"76.19%","16":"50 - 60","17":"55","18":"78.57%","19":"1929","20":"","21":"1929","22":""},"8":{"c":"95","b":"100","a":"60"},"9":{"c":"Good","b":"Singles - 8,000","a":"Good"},"10":{"c":"Good","b":"$50 - 60","a":"Good"},"11":{"b":"8 - 10 houses","a":"Brick $9,000"},"12":{"b":"Ample","a":"Ample"},"13":"Good - improving","14":"Natural scenic residential area. Medium Blue.","15":{"1":"F.C. Devlin, Jr. Field Agent, A. Lawson, Jr. Field Agent, C.A. Fleming - Loan Service Representative","2":"2/25/1937","3":""}}},"C3":{"ad_id":117,"name":null,"holc_grade":"C","sheets":1,"url":"//s3.amazonaws.com/holc/ads/OH/Dayton/1937/C3/{z}/{x}_{y}.png","areaDesc":{"1":{"1":"Dayton","2":"C","3":"3"},"2":"Level","3":"Good transportation; playgrounds; schools; churches; near to industrial plants","4":"None","5":{"g":{"1":"xxxxx","2":"xxxxx"},"f":"20%","e":"None","d":{"1":"No","2":""},"c":{"1":"None","2":""},"b":"1200","a":"Better class laborers - Clerks"},"6":{"d":"fair","c":"40 years","b":"Frame-brick","a":"1 & 2 family detached"},"7":{"1":"$3,500 - 4,500","2":"$4,000","3":"$25 - 35","4":"$30","5":"1933","6":"1,800 - 2,500","7":"2,000","8":"50","9":"12 - 20","10":"15","11":"50","12":"1937","13":"2,500 - 3,500","14":"3,000","15":"75","16":"20 - 27","17":"22","18":"73.3","19":"1929","20":"","21":"1929","22":""},"8":{"c":"70","b":"98","a":"?8"},"9":{"c":"","b":"","a":"None"},"10":{"c":"Good","b":"at $22 rental","a":"Good"},"11":{"b":"","a":"None"},"12":{"b":"","a":"Limited"},"13":"Static","14":"Has good transportation and convenient to Master Electric Co. Trupar Mfg. Company and smaller plants. Low Yellow.","15":{"1":"F.C. Devlin, Jr. Field Agent, A. Lawson, Jr. Field Agent, C.A. Fleming, Loan Service Representative.","2":"March 3, 1937","3":""}}},"C14":{"ad_id":117,"name":null,"holc_grade":"C","sheets":1,"url":"//s3.amazonaws.com/holc/ads/OH/Dayton/1937/C14/{z}/{x}_{y}.png","areaDesc":{"1":{"1":"Harrison Township Adjoining Northwest Dayton","2":"C","3":"14"},"2":"High-rolling","3":"Good schools, wooded section, newer houses.","4":"Not very highly restricted; no improved streets; not very good transportation; some \"jerry built houses\".","5":{"g":{"1":"","2":"xxxxx"},"f":"30%","e":"None","d":{"1":"None","2":""},"c":{"1":"None","2":""},"b":"1,500","a":"Laborers and mechanics"},"6":{"d":"Fair","c":"15 yrs.","b":"Frame","a":"1 family detached 1; and 2 story"},"7":{"1":"$3,800 - 4,500","2":"$4,000","3":"$30 - 38","4":"$32","5":"1933","6":"1,800 - 2,500","7":"2,000","8":"50","9":"12 - 18","10":"15","11":"46.8","12":"1937","13":"3,000 - 3,800","14":"3,200","15":"80","16":"20 - 26","17":"22","18":"68.7","19":"1929","20":"","21":"1929","22":""},"8":{"c":"80","b":"95","a":"40"},"9":{"c":"Fair","b":"1 family $3,200","a":"Fair"},"10":{"c":"Fair","b":"1 family $22","a":"Fair"},"11":{"b":"18 - 20 houses","a":"Single family detached $3,500"},"12":{"b":"Limited","a":"Limited"},"13":"Upward - surrounded by high grade areas.","14":"Low yellow.","15":{"1":"F.C. Devlin, Jr., Field Agent, A. Lawson, Jr. Field Agent, C.A. Fleming, Loans Service Representatives.","2":"","3":""}}},"B7":{"ad_id":117,"name":null,"holc_grade":"B","sheets":1,"url":"//s3.amazonaws.com/holc/ads/OH/Dayton/1937/B7/{z}/{x}_{y}.png","areaDesc":{"1":{"1":"Dayton","2":"B","3":"7"},"2":"High, Level","3":"Fair residential","4":"Mixture of types of houses","5":{"g":{"1":"","2":""},"f":"None","e":"Italian, Jewish","d":{"1":"No","2":""},"c":{"1":"Italian-Jewish","2":"20"},"b":"2,200","a":"Clerks - Mechanics"},"6":{"d":"Fair","c":"30 years","b":"Frame","a":"Singles & Doubles"},"7":{"1":"$6,000 - 8,000","2":"$7,500","3":"$45 - 60","4":"$50","5":"1933","6":"3,500 - 5,000","7":"4,000","8":"53 1/3%","9":"25 - 35","10":"30","11":"60","12":"1937","13":"5,000 - 7,000","14":"6,000","15":"80%","16":"40 - 50","17":"40","18":"80","19":"1929","20":"","21":"1929","22":""},"8":{"c":"40","b":"100","a":"95"},"9":{"c":"Poor","b":"","a":"Poor"},"10":{"c":"Good","b":"$40","a":"Good"},"11":{"b":"","a":"None"},"12":{"b":"","a":"Limited"},"13":"Downward","14":"Property is fairly good at present, but it is reasonable to assume that the section has reached its peak and could almost be classed as yellow. There is still considerable value and some desirability for property located here.","15":{"1":"F.C. Devlin, Jr. Field Agent., A. Lawson Jr., Field Agent, C.A. Fleming, Loan Service Representative","2":"March, 1 1937","3":""}}},"C11":{"ad_id":117,"name":null,"holc_grade":"C","sheets":1,"url":"//s3.amazonaws.com/holc/ads/OH/Dayton/1937/C11/{z}/{x}_{y}.png","areaDesc":{"1":{"1":"Dayton","2":"C","3":"11"},"2":"Level","3":"Good transportation; good schools and playgrounds; all streets improvements.","4":"None.","5":{"g":{"1":"xxxxx","2":"xxxxx"},"f":"10%","e":"Foreign-Jewish","d":{"1":"No","2":""},"c":{"1":"Russian Jewish German-Polish","2":"80"},"b":"2,400","a":"Business men-Jr. Executives"},"6":{"d":"Fair","c":"25 years","b":"Frame & Brick","a":"1 family predominating 1,2, & 4 family detached"},"7":{"1":"$6,500 - 7,000","2":"7,000","3":"$50 - 65","4":"$60","5":"1933","6":"3,000 - 4,000","7":"3,500","8":"50%","9":"25 - 35","10":"30","11":"50","12":"1937","13":"4,800 - 6,000","14":"5,200","15":"74.30%","16":"45 - 55","17":"50","18":"83.30%","19":"1929","20":"","21":"1929","22":""},"8":{"c":"60","b":"95","a":"90"},"9":{"c":"Fair","b":"Single Family $5,500","a":"Fair"},"10":{"c":"Good","b":"Single house & apartment at $50","a":"Good"},"11":{"b":"","a":"None"},"12":{"b":"Ample","a":"Ample"},"13":"Downward","14":"Foreign born Jewish centering in this area. Low yellow.","15":{"1":"F.C. Devlin, Jr. Field Agent, A. Lawson Jr., Field Agent., C.A. Fleming, Loan Service Representative.","2":"March 8, 1937","3":""}}},"D9":{"ad_id":117,"name":null,"holc_grade":"D","sheets":1,"url":"//s3.amazonaws.com/holc/ads/OH/Dayton/1937/D9/{z}/{x}_{y}.png","areaDesc":{"1":{"1":"Dayton","2":"D","3":"9"},"2":"Level","3":"Good transportation - good schools","4":"Older section of city, negroes moving in.","5":{"g":{"1":"xxxxx","2":"xxxxx"},"f":"25%","e":"Negro","d":{"1":"Yes","2":"15"},"c":{"1":"Slavs","2":"15"},"b":"1500","a":"Clerks - Laborers"},"6":{"d":"fair","c":"40 years","b":"frame & brick","a":"1 family and 2 family detached and apartments"},"7":{"1":"","2":"$4,000","3":"","4":"$30","5":"1933","6":"","7":"1800","8":"45","9":"","10":"20","11":"66.6","12":"1937","13":"","14":"2800","15":"70","16":"","17":"25","18":"83.3","19":"1929","20":"","21":"1929","22":""},"8":{"c":"50","b":"100","a":"95"},"9":{"c":"","b":"","a":"None"},"10":{"c":"Good","b":"Anything available $25.","a":"Good"},"11":{"b":"","a":"None"},"12":{"b":"","a":"Limited"},"13":"Downward","14":"Close to city; trend towards room houses and apartments. Low Red.","15":{"1":"F.C. Devlin, Jr., Field Agent. A. Lawson, Jr., Field Agent, C.A. Fleming, Loan Service Representative","2":"March 10, 1937","3":""}}},"B3":{"ad_id":117,"name":null,"holc_grade":"B","sheets":1,"url":"//s3.amazonaws.com/holc/ads/OH/Dayton/1937/B3/{z}/{x}_{y}.png","areaDesc":{"1":{"1":"Van Buren Township - Southern Hills, West of Oakwood","2":"B","3":"3"},"2":"High - rolling","3":"Fairly good residential section - we'll restricted","4":"None","5":{"g":{"1":"Slowly","2":""},"f":"None","e":"None","d":{"1":"None","2":""},"c":{"1":"None","2":""},"b":"2400","a":"Middle Class"},"6":{"d":"Fair","c":"20 yrs.","b":"Frame & Brick","a":"1 family detached"},"7":{"1":"6,000 - 8,000","2":"7,000","3":"40 - 60","4":"50","5":"1933","6":"4,000 - 5,600","7":"4,800","8":"68.57%","9":"25 - 35","10":"30","11":"60%","12":"1937","13":"5,000 - 6,500","14":"5,750","15":"82.14%","16":"40 - 45","17":"40","18":"80%","19":"1929","20":"","21":"1929","22":""},"8":{"c":"100","b":"100","a":"60"},"9":{"c":"fair","b":"6,000 singles","a":"Fair"},"10":{"c":"good","b":"40","a":"good"},"11":{"b":"8 - 10 houses","a":"brick & frame 6500"},"12":{"b":"ample","a":"singles"},"13":"Static","14":"Portion of section has only township fire protection - no police protection. Medium blue.","15":{"1":"F.C. Devlin, Jr. Field Agent, A. Lawson, Jr., Field Agent. C.A. Fleming - Loan Service Representative.","2":"February 25, 1937","3":""}}},"B10":{"ad_id":117,"name":null,"holc_grade":"B","sheets":1,"url":"//s3.amazonaws.com/holc/ads/OH/Dayton/1937/B10/{z}/{x}_{y}.png","areaDesc":{"1":{"1":"Dayton","2":"B","3":"10"},"2":"High - rolling","3":"Homogeneous residential area of modest homes.","4":"None","5":{"g":{"1":"Fast","2":""},"f":"None","e":"None","d":{"1":"No","2":""},"c":{"1":"None","2":""},"b":"2,500","a":"Jr. Executives - Middle Class"},"6":{"d":"Good - some only fair","c":"10 - 15 years","b":"Frame - some brick","a":"1 family & few doubles"},"7":{"1":"$6,500 - 8,000","2":"7,500","3":"$40 - 60","4":"50","5":"1933","6":"3,000 - 4,000","7":"3,500","8":"46.6","9":"25 - 35","10":"25","11":"50","12":"5,500 - 6,500","13":"6,000","14":"80","15":"40 - 50","16":"45","17":"90%","18":"1929","19":"","20":"1929","21":"","22":""},"8":{"c":"70","b":"99","a":"70"},"9":{"c":"Good","b":"$6,500","a":"Good"},"10":{"c":"Good","b":"$45","a":"Good"},"11":{"b":"45 - 50 houses $7,000","a":"Brick"},"12":{"b":"Ample","a":"Ample"},"13":"Upward","14":"In the extreme N.W. corner there is a spotty section of houses needed only minor repair. Medium Blue.","15":{"1":"F.C. Devlin, Jr., Field Agent, C.A. Fleming Loan Service Representative, A. Lawson, Jr., Field Agent.","2":"March 3, 1937","3":""}}},"D8":{"ad_id":117,"name":null,"holc_grade":"D","sheets":1,"url":"//s3.amazonaws.com/holc/ads/OH/Dayton/1937/D8/{z}/{x}_{y}.png","areaDesc":{"1":{"1":"Dayton","2":"D","3":"8"},"2":"Low","3":"Adjacent to center of city; good transportation; good schools.","4":"Very low; one of oldest sections of city.","5":{"g":{"1":"xxxxx","2":"xxxxx"},"f":"15%","e":"None","d":{"1":"None","2":""},"c":{"1":"None","2":""},"b":"1200","a":"Clerks-mechanics"},"6":{"d":"fair","c":"50 years","b":"Frame","a":"1 & 2 family detached"},"7":{"1":"","2":"$4,000","3":"","4":"$35","5":"1933","6":"","7":"2000","8":"50","9":"","10":"17","11":"48.5","12":"1937","13":"","14":"2750","15":"68.7","16":"","17":"27","18":"77.1","19":"1929","20":"","21":"1929","22":""},"8":{"c":"30","b":"100","a":"95"},"9":{"c":"","b":"","a":"None"},"10":{"c":"Good","b":"Apartments & 1 family $27.50","a":"Good"},"11":{"b":"","a":"None"},"12":{"b":"","a":"None"},"13":"Downward","14":"Some of the larger older type houses are being made into two and three family apartments. Also becoming a rooming house area. Medium Red.","15":{"1":"F.C. Devlin, Jr., Field Agent. A. Lawson, Jr., Field Agent, C.A. Fleming - Loan Service Representative.","2":"March 10, 1937","3":""}}},"D14":{"ad_id":117,"name":null,"holc_grade":"D","sheets":1,"url":"//s3.amazonaws.com/holc/ads/OH/Dayton/1937/D14/{z}/{x}_{y}.png","areaDesc":{}},"C12":{"ad_id":117,"name":null,"holc_grade":"C","sheets":1,"url":"//s3.amazonaws.com/holc/ads/OH/Dayton/1937/C12/{z}/{x}_{y}.png","areaDesc":{"1":{"1":"Dayton & Madison Township West of Dayton","2":"C","3":"12"},"2":"High, level","3":"Good transportation; good schools; good playgrounds; newer section of medium priced houses with similar type houses; reasonable residential restrictions.","4":"Necessary to travel through colored section to get to it.","5":{"g":{"1":"","2":"xxxxx"},"f":"20%","e":"None","d":{"1":"None","2":""},"c":{"1":"None","2":""},"b":"1,800","a":"Mechanics, laborers, clerks"},"6":{"d":"Good","c":"15 years","b":"Frame","a":"1 & 2 family detached 5 & 6 rooms"},"7":{"1":"$4,000 - 5,500","2":"4,500","3":"35 - 45","4":"40","5":"1933","6":"2,000 - 3,000","7":"2,500","8":"55.50%","9":"18 - 28","10":"20","11":"50","12":"1937","13":"3,800 - 4,800","14":"4,000","15":"88.8","16":"25 - 35","17":"30","18":"75","19":"1929","20":"","21":"1929","22":""},"8":{"c":"70","b":"100","a":"60"},"9":{"c":"Good","b":"Single family detached $3,800","a":"Good"},"10":{"c":"Good","b":"Single family detached $30","a":"Good"},"11":{"b":"25 - 30","a":"1 family detached 1000"},"12":{"b":"Ample","a":"Ample"},"13":"Upward","14":"Section known as Westwood adjacent to Inland Manufacturing Company plant, a General Motors Corporation subsidiary. Medium yellow.","15":{"1":"D.C. Devlin, Jr., Field Agent A. Lawson, Jr. Field Agent, C.A. Fleming, Loan Service Representative.","2":"March 10, 1937","3":""}}},"D10":{"ad_id":117,"name":null,"holc_grade":"D","sheets":1,"url":"//s3.amazonaws.com/holc/ads/OH/Dayton/1937/D10/{z}/{x}_{y}.png","areaDesc":{"1":{"1":"Dayton","2":"D","3":"10"},"2":"Level","3":"Good transportation and schools.","4":"Mixture of low class foreigners - Polish, Russian, Hungarian and negro. Old houses in bad repair.","5":{"g":{"1":"Yes","2":"80%"},"f":"","e":"Lower class foreigners","d":{"1":"Yes","2":"10"},"c":{"1":"Hungarian, Slavs, Polish, Russian","2":""},"b":"900","a":"Laborers"},"6":{"d":"Poor","c":"40 years","b":"Frame","a":"1 & 2 family detached"},"7":{"1":"","2":"$2,500","3":"","4":"$22","5":"1933","6":"","7":"1000","8":"40","9":"","10":"10","11":"45.4","12":"1937","13":"","14":"1800","15":"72","16":"","17":"15","18":"68.1","19":"1929","20":"","21":"1929","22":""},"8":{"c":"50","b":"95","a":"95"},"9":{"c":"","b":"","a":"None"},"10":{"c":"Fair","b":"Any available $15","a":"Fair"},"11":{"b":"","a":"None"},"12":{"b":"","a":"None"},"13":"Downward","14":"Low Red.","15":{"1":"F.C. Devlin, Jr., Field Agent. A. Lawson, Jr., FIeld Agent. C.A. Fleming, - Loan Service Representative","2":"March 10, 1937","3":""}}},"B1":{"ad_id":117,"name":null,"holc_grade":"B","sheets":1,"url":"//s3.amazonaws.com/holc/ads/OH/Dayton/1937/B1/{z}/{x}_{y}.png","areaDesc":{"1":{"1":"Van Buren, Township-South of Oakwood","2":"B","3":"1"},"2":"High - level","3":"Desirable residential section - restricted - good schools.","4":"None","5":{"g":{"1":"Moderately","2":""},"f":"None","e":"None","d":{"1":"None","2":""},"c":{"1":"None","2":""},"b":"2,400","a":"Skilled mechanics"},"6":{"d":"good","c":"10 years","b":"frame and brick","a":"1 family detached"},"7":{"1":"6,000 - 8,500","2":"$7,000","3":"No rentals","4":"","5":"1933","6":"3,800 - 5,800","7":"4,500","8":"64.30%","9":"","10":"","11":"","12":"1937","13":"5,000 - 7,000","14":"5,500","15":"78.57%","16":"","17":"","18":"","19":"1929","20":"","21":"1929","22":""},"8":{"c":"100","b":"100","a":"50"},"9":{"c":"fair","b":"$6,000 singles","a":"Fair"},"10":{"c":"- - -","b":"- - -","a":"no rentals"},"11":{"b":"15 - 18 houses","a":"Brick & frame $6,800 - 7,000"},"12":{"b":"yes","a":"yes"},"13":"improving - good","14":"Outside city limits - township fire protection - no police protection no vandalism - Medium blue.","15":{"1":"F.C. Devlin, Jr. Field Agent, A. Lawson, Jr. Field Agent, C.A. Fleming - Loan Service Repre.","2":"February 25, 1937","3":""}}},"C8":{"ad_id":117,"name":null,"holc_grade":"C","sheets":1,"url":"//s3.amazonaws.com/holc/ads/OH/Dayton/1937/C8/{z}/{x}_{y}.png","areaDesc":{"1":{"1":"Van Buren Township, East of Oakwood","2":"C","3":"C-8"},"2":"High level","3":"Good schools; restricted (not highly); sewers & water","4":"Transportation poor, no gas.","5":{"g":{"1":"","2":"xxxxx"},"f":"None","e":"None","d":{"1":"None","2":""},"c":{"1":"None","2":""},"b":"1,500","a":"Better class laborer-clerks"},"6":{"d":"Good","c":"15 years","b":"frame","a":"Single family detached 5 & 6 rooms"},"7":{"1":"$4,500 - 5,500","2":"5,000","3":"$35 - 45","4":"40","5":"1933","6":"2,500 - 3,000","7":"2,800","8":"62.50%","9":"20 - 30","10":"25","11":"56","12":"1937","13":"3,500 - 4,500","14":"3,800","15":"87.50%","16":"30 - 40","17":"35","18":"76","19":"1929","20":"","21":"1929","22":""},"8":{"c":"95","b":"100","a":"30"},"9":{"c":"Fair","b":"Single family $4000","a":"Fair"},"10":{"c":"Good","b":"Single family $35","a":"Good"},"11":{"b":"15 - 20","a":"Single family detached 5 & 6 room $4,000"},"12":{"b":"Ample","a":"Ample"},"13":"Upward","14":"Medium Yellow","15":{"1":"F.C. Devlin, Jr., Field Agent, A. Lawson, Jr., Field Agent, C.A. Fleming, Loan Service Representative.","2":"March 8, 1937","3":""}}},"D5":{"ad_id":117,"name":null,"holc_grade":"D","sheets":1,"url":"//s3.amazonaws.com/holc/ads/OH/Dayton/1937/D5/{z}/{x}_{y}.png","areaDesc":{"1":{"1":"Mad River Township, East of Dayton","2":"D","3":"5"},"2":"Low","3":"Good schools","4":"Poor transportation; low class white; poorly constructed buildings","5":{"g":{"1":"","2":"xxxxx"},"f":"40%","e":"Foreign born","d":{"1":"None","2":""},"c":{"1":"Hungarian-Polish","2":"20"},"b":"900","a":"Laborers"},"6":{"d":"Poor","c":"18 yrs","b":"Frame","a":"1 family detached and shacks"},"7":{"1":"","2":"$3,000","3":"","4":"$25","5":"1933","6":"","7":"1200","8":"40","9":"","10":"15","11":"60","12":"1937","13":"","14":"1800","15":"60","16":"","17":"20","18":"80","19":"1929","20":"","21":"1929","22":""},"8":{"c":"60","b":"100","a":"50"},"9":{"c":"","b":"","a":"None"},"10":{"c":"Good","b":"Single family detached $20","a":"Good"},"11":{"b":"","a":"none"},"12":{"b":"","a":"none"},"13":"Downward","14":"Along highway approaching Wright Field, U.S. Army Post. Low Red.","15":{"1":"F.C. Devlin, Jr., Field Agent, A.Lawson, Jr., Field Agent. C.A. Fleming, Loan Service Representative.","2":"March 9, 1937","3":""}}},"D11":{"ad_id":117,"name":null,"holc_grade":"D","sheets":1,"url":"//s3.amazonaws.com/holc/ads/OH/Dayton/1937/D11/{z}/{x}_{y}.png","areaDesc":{"1":{"1":"Dayton","2":"D","3":"11"},"2":"Level","3":"Good schools and transportation","4":"Mixture negro and poor white.","5":{"g":{"1":"xxxxx","2":"xxxxx"},"f":"80%","e":"Negro","d":{"1":"Yes","2":"80"},"c":{"1":"None","2":""},"b":"700","a":"Laborers"},"6":{"d":"Poor","c":"40 years","b":"Frame","a":"1 & 2 family detached"},"7":{"1":"","2":"$2,000","3":"","4":"$15","5":"","6":"400","7":"20","8":"","9":"9","10":"60","11":"","12":"1937","13":"","14":"900","15":"45","16":"","17":"12","18":"80","19":"1929","20":"","21":"1929","22":""},"8":{"c":"50","b":"95","a":"95"},"9":{"c":"","b":"","a":"None"},"10":{"c":"Fair","b":"Anything available $12.","a":"Fair"},"11":{"b":"","a":"None"},"12":{"b":"","a":"None"},"13":"Downward","14":"Low Red.","15":{"1":"F.C. Devlin, Jr., Field Agent. A. Lawson, Jr., Field Agent. C.A. Fleming - Loan Service Representative.","2":"March 10, 1937","3":""}}},"C13":{"ad_id":117,"name":null,"holc_grade":"C","sheets":1,"url":"//s3.amazonaws.com/holc/ads/OH/Dayton/1937/C13/{z}/{x}_{y}.png","areaDesc":{"1":{"1":"Dayton","2":"C","3":"13"},"2":"Level-low","3":"Close by industrial plants; good transportation and schools; newer type houses similar in type; highly restricted against colored.","4":"Surrounded by colored section.","5":{"g":{"1":"xxxxx","2":"xxxxx"},"f":"20%","e":"None","d":{"1":"None","2":""},"c":{"1":"None","2":""},"b":"1,500","a":"Mechanics, better class of laborer"},"6":{"d":"Fair","c":"20 yrs.","b":"Frame","a":"1 & 2 family single detached"},"7":{"1":"4,000 - 5,500","2":"4,500","3":"30 - 38","4":"32","5":"1933","6":"2,000 - 2,800","7":"2,200","8":"48.8","9":"15 - 25","10":"18","11":"56.20%","12":"1937","13":"2,800 - 3,800","14":"3,000","15":"66.6","16":"25 - 30","17":"28","18":"87.50%","19":"1929","20":"","21":"1929","22":""},"8":{"c":"75","b":"95","a":"85"},"9":{"c":"","b":"","a":"None"},"10":{"c":"Good","b":"$28 Single family","a":"Good"},"11":{"b":"","a":"None"},"12":{"b":"Limited","a":"Limited"},"13":"Downward","14":"Section known as Whittier Terrace adjacent to Delco Brake Corp. a subsidiary of General Motors Corporation. Low yellow.","15":{"1":"F.C. Devlin, Jr., Field Agent, A. Lawson, Jr., Field Agent, C.A. Fleming - Loan Service Representative","2":"March 10, 1937","3":""}}},"D12":{"ad_id":117,"name":null,"holc_grade":"D","sheets":1,"url":"//s3.amazonaws.com/holc/ads/OH/Dayton/1937/D12/{z}/{x}_{y}.png","areaDesc":{"1":{"1":"Dayton","2":"D","3":"12"},"2":"Low","3":"Good transportation; adjoins center of city.","4":"Zoned for business; old houses.","5":{"g":{"1":"xxxxx","2":"xxxxx"},"f":"20","e":"Business","d":{"1":"None","2":""},"c":{"1":"Greeks","2":"20"},"b":"1200","a":"Clerks - laborers"},"6":{"d":"Fair","c":"50 years","b":"Brick and frame","a":"1 & 2 family detached & apartments"},"7":{"1":"","2":"9500","3":"","4":"50","5":"1933","6":"","7":"4000","8":"42.1","9":"","10":"25","11":"50","12":"1937","13":"","14":"7000","15":"73.6","16":"","17":"40","18":"80","19":"1929","20":"","21":"1929","22":""},"8":{"c":"20","b":"100","a":"100"},"9":{"c":"","b":"","a":"None"},"10":{"c":"Good","b":"Anything available $40","a":"Good"},"11":{"b":"","a":"None"},"12":{"b":"","a":"Limited"},"13":"Downward to business","14":"Larger older type houses being converted into income properties by converting into small apartments and rooming houses. Medium red.","15":{"1":"F.C. Devlin, Jr., Field Agent, A. Lawson, Jr., Field Agent, C.A. Fleming - Loan Service Representative.","2":"March 10, 1937","3":""}}},"C7":{"ad_id":117,"name":null,"holc_grade":"C","sheets":1,"url":"//s3.amazonaws.com/holc/ads/OH/Dayton/1937/C7/{z}/{x}_{y}.png","areaDesc":{"1":{"1":"Van Buren Township-West of Oakwood","2":"C","3":"C-7"},"2":"High-level","3":"Wooded suburban section with fair transportation; good schools; churches; uniform type of home.","4":"None","5":{"g":{"1":"","2":"xxxxx"},"f":"None","e":"None","d":{"1":"None","2":""},"c":{"1":"None","2":""},"b":"1,500","a":"Mechanics-Clerks-Better class laborer"},"6":{"d":"Good","c":"15 yrs.","b":"Frame","a":"Single 5 & 6 rooms 1 & 2 story detached"},"7":{"1":"5,000 - 6,000","2":"$5,500","3":"$35 - 45","4":"$40","5":"1933","6":"2,500 - 3,500","7":"3,000","8":"54.50%","9":"25 - 30","10":"25","11":"62.50%","12":"1937","13":"4,000 - 5,000","14":"4,500","15":"81.80%","16":"30 - 40","17":"35","18":"87.50%","19":"1929","20":"","21":"1929","22":""},"8":{"c":"100","b":"100","a":"50"},"9":{"c":"","b":"Single family detached $4,500","a":"Good"},"10":{"c":"","b":"Single family detached $35","a":"Good"},"11":{"b":"6/8/2016","a":"Single family detached Frame $4,500"},"12":{"b":"Ample","a":"Ample"},"13":"Upward","14":"Medium Yellow","15":{"1":"F.C. Devlin, Jr. Field Agent, A. Lawson Jr. Field Agent, C.A. Fleming, Loan Service Representative.","2":"March 5, 1937","3":""}}},"C15":{"ad_id":117,"name":null,"holc_grade":"C","sheets":1,"url":"//s3.amazonaws.com/holc/ads/OH/Dayton/1937/C15/{z}/{x}_{y}.png","areaDesc":{"1":{"1":"Van Buren Township, Southeast of Oakwood","2":"C","3":"C-15"},"2":"High - Level.","3":"Good schools","4":"Outside city limits; poor transportation; no street improvements.","5":{"g":{"1":"","2":"xxxxx"},"f":"25%","e":"None","d":{"1":"None","2":""},"c":{"1":"None","2":""},"b":"1,200","a":"Laborer"},"6":{"d":"Fair","c":"15 years","b":"Frame","a":"Single family detached 1 & 2 story"},"7":{"1":"$3,000 - 4,000","2":"3,500","3":"25 - 30","4":"27","5":"1933","6":"1,500 - 2,200","7":"1,800","8":"51.40%","9":"12 - 116","10":"14","11":"51.80%","12":"1937","13":"2,000 - 2,500","14":"2,200","15":"62.80%","16":"20 - 25","17":"22","18":"81.40%","19":"1929","20":"","21":"1929","22":""},"8":{"c":"90","b":"95","a":"40"},"9":{"c":"Fair","b":"Single Family $2200","a":"Fair"},"10":{"c":"Fair","b":"Single Family $20","a":"Fair"},"11":{"b":"12 - 15 houses","a":"1 family 1 story detached $2500"},"12":{"b":"Limited","a":"Limited"},"13":"Upward","14":"Low Yellow","15":{"1":"F.C. Devlin, Jr., Jield Agent, A. Lawson, Jr., Field Agent, C.A. Fleming, Loan Service Representative.","2":"March 10, 1937","3":""}}},"D6":{"ad_id":117,"name":null,"holc_grade":"D","sheets":1,"url":"//s3.amazonaws.com/holc/ads/OH/Dayton/1937/D6/{z}/{x}_{y}.png","areaDesc":{"1":{"1":"Mad River Township, Northeast of Dayton","2":"D","3":"6"},"2":"Low","3":"Good schools.","4":"Poor transportation; plant unrestricted; no improvements.","5":{"g":{"1":"xxxxx","2":"xxxxx"},"f":"90%","e":"Negro","d":{"1":"30% yes","2":"30"},"c":{"1":"Polish-Hungarian","2":"20"},"b":"700","a":"Lowest type laborer"},"6":{"d":"Poor","c":"18 yrs.","b":"Frame","a":"Single family detached & shacks"},"7":{"1":"","2":"$1,500","3":"","4":"$12","5":"1933","6":"","7":"500","8":"33 1/3 %","9":"","10":"5","11":"41.6","12":"1937","13":"","14":"900","15":"60%","16":"","17":"8","18":"66.6","19":"1929","20":"","21":"1929","22":""},"8":{"c":"60","b":"95","a":"50"},"9":{"c":"","b":"","a":"None"},"10":{"c":"","b":"","a":"None"},"11":{"b":"","a":"None"},"12":{"b":"","a":"None"},"13":"Downward","14":"Entire area built up with poorly constructed buildings and shacks. Very poor class of white people intermingling with negro. Low Red.","15":{"1":"F.C. Devlin, Jr., Field Agent, A. Lawson, Jr., Field Agent, C.A. Fleming - Loan Service Representative","2":"March 9, 1937","3":""}}},"B11":{"ad_id":117,"name":null,"holc_grade":"B","sheets":1,"url":"//s3.amazonaws.com/holc/ads/OH/Dayton/1937/B11/{z}/{x}_{y}.png","areaDesc":{"1":{"1":"Harrison Township, North of Dayton","2":"B","3":"11"},"2":"High - rolling","3":"Wooded tract fronting on river","4":"None","5":{"g":{"1":"Slowly","2":""},"f":"None","e":"None","d":{"1":"None","2":""},"c":{"1":"None","2":""},"b":"2,500 - 3,000","a":"Jr. Executives - Middle Class"},"6":{"d":"Good","c":"8 - 10 years","b":"Brick, Stone, Frame","a":"1 family detached"},"7":{"1":"$8,000 - 15,000","2":"$9,000","3":"","4":"","5":"1933","6":"4,500 - 6,000","7":"5,000","8":"55.50%","9":"No Rentals","10":"","11":"","12":"1937","13":"6,000 - 8,000","14":"7,000","15":"77.70%","16":"","17":"","18":"","19":"1929","20":"","21":"1929","22":""},"8":{"c":"100","b":"100","a":"25"},"9":{"c":"Fair","b":"$7,000 Single","a":"Fair"},"10":{"c":"","b":"","a":"No rentals"},"11":{"b":"12 - 15 houses $8,000","a":"Brick-Stone"},"12":{"b":"Ample","a":"Ample"},"13":"Upward","14":"Medium Blue","15":{"1":"F.C. Devlin, Jr. Field Agent, A. Lawson, Jr. Field Agent, C.A. Fleming, Loan Service Representative","2":"March, 3 1937","3":""}}},"D1":{"ad_id":117,"name":null,"holc_grade":"D","sheets":1,"url":"//s3.amazonaws.com/holc/ads/OH/Dayton/1937/D1/{z}/{x}_{y}.png","areaDesc":{"1":{"1":"Van Buren Township, southeast of Oakwood","2":"D","3":"1"},"2":"High - Level","3":"None","4":"Poor transportation, outside city limits, unrestricted unimproved.","5":{"g":{"1":"","2":"xxxxx"},"f":"40%","e":"Lower class","d":{"1":"None","2":""},"c":{"1":"None","2":""},"b":"900","a":"Laborers"},"6":{"d":"Poor","c":"12 years","b":"Frame","a":"1 family, 1 story singles-shacks"},"7":{"1":"$2500 - 3500","2":"$3,000","3":"$18 - 22","4":"$20","5":"1933","6":"1000 - 1800","7":"1200","8":"40%","9":"8 - 12","10":"10","11":"50","12":"1937","13":"1600 - 2200","14":"1800","15":"60%","16":"13 - 18","17":"15","18":"75","19":"1929","20":"","21":"1929","22":""},"8":{"c":"80","b":"100","a":"30"},"9":{"c":"Poor","b":"1 family 1 story $2000","a":"Poor"},"10":{"c":"Fair","b":"1 family 1 story $15","a":"Fair"},"11":{"b":"5-8 houses","a":"1 family 1 story frame $2500"},"12":{"b":"Limited","a":"Limited"},"13":"Cheaper class home - upward","14":"At present time area is spotted with shacks; houses are built on the rear of lots. As general conditions improve it is expected that there will be an increase in the cheaper type of home. Low Red.","15":{"1":"F.C. Devlin, Jr. Field Agent, A. Lawson, Jr. Field Agent, C.A.Fleming, Loan Service Representative.","2":"March 8, 1937","3":""}}},"C4":{"ad_id":117,"name":null,"holc_grade":"C","sheets":1,"url":"//s3.amazonaws.com/holc/ads/OH/Dayton/1937/C4/{z}/{x}_{y}.png","areaDesc":{"1":{"1":"Dayton","2":"C","3":"4"},"2":"Southern part - high - Northern part - Low","3":"Transportation and schools good; all street improvement","4":"Properties old.","5":{"g":{"1":"xxxxx","2":"xxxxx"},"f":"10%","e":"No","d":{"1":"None","2":""},"c":{"1":"No undesirables","2":""},"a":"Better class laborers-clerks","b":"1,500"},"6":{"d":"Fair","c":"40 years","b":"Brick frame","a":"1 & 2 family detached"},"7":{"1":"4,500 - 5,500","2":"$5,000","3":"$32 - 42","4":"38","5":"1933","6":"2,000 - 3,000","7":"2,500","8":"50","9":"20 - 30","10":"25","11":"65.70%","12":"1937","13":"3,000 - 4,000","14":"3,500","15":"70","16":"25 - 35","17":"30","18":"71%","19":"1929","20":"","21":"1929","22":""},"8":{"c":"60","b":"100","a":"98"},"9":{"c":"None","b":"","a":"None"},"10":{"c":"Good","b":"1 fam. detached $30","a":"Good"},"11":{"b":"","a":"None"},"12":{"b":"none","a":"none"},"13":"Downward","14":"Medium yellow.","15":{"1":"F.C. Devlin, Jr., Field Agent. A. Lawson, Jr. Field Agent, C.A. Fleming, Loan Service Representative.","2":"March 5, 1937","3":""}}},"A3":{"ad_id":117,"name":null,"holc_grade":"A","sheets":1,"url":"//s3.amazonaws.com/holc/ads/OH/Dayton/1937/A3/{z}/{x}_{y}.png","areaDesc":{"1":{"1":"Oakwood","2":"A","3":"3"},"2":"Level - high","3":"Highly restricted - very high class residential - Exceptionally good schools - parks - playgrounds - homogeneous as to development and character of property - transportation good -- good fire and police protection.","4":"None","5":{"g":{"1":"","2":""},"f":"None","e":"None","d":{"1":"No","2":""},"c":{"1":"None","2":""},"b":"5,000","a":"Professional & Executives"},"6":{"d":"Good","c":"18-20 years","b":"Good","a":"Single family detached"},"7":{"1":"15,000 - 18,000","2":"$16,000","3":"No rental scale","4":"","5":"1933","6":"10,000-12,000","7":"11,000","8":"68 3/4","9":"","10":"","11":"","12":"1937","13":"12,000  - 15,000","14":"13,000","15":"84 3/8","16":"","17":"","18":"","19":"1929","20":"","21":"1929","22":""},"8":{"c":"100","b":"100","a":"100"},"9":{"c":"good","b":"$12,000 - 10,500","a":"Good"},"10":{"c":"","b":"","a":"Few rental units"},"11":{"b":"8-10 houses","a":"Single family detached"},"12":{"b":"Good","a":"Good"},"13":"Upward","14":"Wooded section -- all business centered outside area. Medium Green.","15":{"1":"F.C. Devlin, Jr. Field Agent, A. Lawson, Jr. Field Agent, C.A. Fleming - Loan Service Rep.","2":"February 25, 1937","3":""}}},"A2":{"ad_id":117,"name":null,"holc_grade":"A","sheets":1,"url":"//s3.amazonaws.com/holc/ads/OH/Dayton/1937/A2/{z}/{x}_{y}.png","areaDesc":{"1":{"1":"Oakwood","2":"A","3":"2"},"2":"Level-high","3":"Highly restricted-very high class residential - exceptionally good schools - parks - playgrounds - homogeneous as to development and character of property - transportation good - good fire and police protection","4":"None","5":{"g":{"1":"moderately","2":""},"f":"None","e":"None","d":{"1":"No","2":""},"c":{"1":"None","2":""},"b":"5,000","a":"Professional & Executives"},"6":{"d":"Excellent","c":"10 years","b":"Brick","a":"single-family detached"},"7":{"1":"11,000 - 20,000","2":"15,000","3":"No rental scale","4":"","5":"1933","6":"8,000  - 15,000","7":"10,000","8":"66 2/3","9":"","10":"","11":"","12":"1937","13":"10,000 - 17,000","14":"12,000","15":"80","16":"","17":"","18":"","19":"1929","20":"","21":"1929","22":""},"8":{"c":"100","b":"100","a":"60"},"9":{"c":"Good","b":"10,000 - 12,000","a":"Fair"},"10":{"c":"","b":"","a":"Few rental units"},"11":{"b":"15-18 houses","a":"Brick detached $15,000"},"12":{"b":"good","a":"good"},"13":"Upward","14":"All business centered in one section. Medium Green.","15":{"1":"F. C. Devlin, Jr. Field Agent, A. Lawson Jr., Field Agent, C. A. Fleming Loan, Service Representative.","2":"February 25, 1937","3":""}}},"A4":{"ad_id":117,"name":null,"holc_grade":"A","sheets":1,"url":"//s3.amazonaws.com/holc/ads/OH/Dayton/1937/A4/{z}/{x}_{y}.png","areaDesc":{"1":{"1":"Oakwood & part of Southern Hill section","2":"A","3":"4"},"2":"Rolling to hilly","3":"Wooded section of acre tracts - Oakwood schools - restricted - very high class residential - parks - playgrounds - homogeneous as to development and character of property - transportation good - good fire and police protection.","4":"None","5":{"g":{"1":"Moderately","2":""},"f":"None","e":"None","d":{"1":"None","2":""},"c":{"1":"None","2":""},"b":"over 10,000","a":"Professional & executives"},"6":{"d":"excellent","c":"15 - 18 years","b":"stone and brick","a":"one family detached"},"7":{"1":"40,000 - 100,000","2":"-","3":"No rental units","4":"","5":"1933","6":"No sales to change range","7":"","8":"","9":"","10":"","11":"","12":"","13":"","14":"","15":"","16":"","17":"","18":"","19":"1929","20":"","21":"1929","22":""},"8":{"c":"100","b":"100","a":"50"},"9":{"c":"Good","b":"----","a":"Good"},"10":{"c":"- - -","b":"----","a":"Not applicable"},"11":{"b":"15-16 houses","a":"Brick singles & stone"},"12":{"b":"Good","a":"Good"},"13":"upward","14":"Financing done primarily through insurance companies. High green.","15":{"1":"F.e. Devlin, Jr. Field Agent, A. Lawson Jr. Field Agent - C.A. Fleming - loan service representative","2":"February 25, 1937","3":""}}},"A5":{"ad_id":117,"name":null,"holc_grade":"A","sheets":1,"url":"//s3.amazonaws.com/holc/ads/OH/Dayton/1937/A5/{z}/{x}_{y}.png","areaDesc":{"1":{"1":"Oakwood & small part of Van Buren Township","2":"A","3":"A-5"},"2":"Hilly","3":"Highly restricted - good schools - good transportation - wooded section.","4":"None","5":{"g":{"1":"Moderately","2":""},"f":"None","e":"None","d":{"1":"None","2":""},"c":{"1":"None","2":""},"b":"4,000","a":"Junior executive & professional"},"6":{"d":"Good","c":"12 years","b":"Brick","a":"Single family detached 6 & 7 rooms."},"7":{"1":"$12,000 - 14,000","2":"$13,000","3":"No rental scale","4":"","5":"1933","6":"7,000 - 8,000","7":"7.5","8":"57.70%","9":"","10":"","11":"","12":"1937","13":"9,000 - 10,000","14":"9,500","15":"73.08%","16":"","17":"","18":"","19":"1929","20":"","21":"1929","22":""},"8":{"c":"100","b":"100","a":"60"},"9":{"c":"Good","b":"Single detached $10,000","a":"Good"},"10":{"c":"","b":"- - - - --","a":"None"},"11":{"b":"15 - 18","a":"Single family detached, brick & stone"},"12":{"b":"Good","a":"Good"},"13":"Upward","14":"Mortgage financing by insurance companies and locally. Medium Green.","15":{"1":"F.C. Devlin - Jr. Field Agent. A. Lawson, Jr. Field Agent, C.A. Fleming - Loan Service Representative","2":"February 25, 1937","3":""}}},"A1":{"ad_id":117,"name":null,"holc_grade":"A","sheets":1,"url":"//s3.amazonaws.com/holc/ads/OH/Dayton/1937/A1/{z}/{x}_{y}.png","areaDesc":{"1":{"1":"Oakwood","2":"A","3":"1"},"2":"Level - high","3":"Restricted - very high class residential - exceptionally good schools - parks - playgrounds - homogeneous as to development and character of property - transportation good - good fire and police protection.","4":"None.","5":{"g":{"1":"Fast","2":""},"f":"None","e":"None","d":{"1":"No","2":""},"c":{"1":"None","2":""},"b":"2,500","a":"Middle class, junior executive, skilled mechanics"},"6":{"d":"good to excellent","c":"10 years","b":"Frame and brick","a":"Single family detached"},"7":{"1":"7,000 - 9,000","2":"7,500","3":"60 - 75","4":"60","5":"","6":"4,500 - 6,000","7":"5,000","8":"66 2/3","9":"35 - 45","10":"35","11":"58 1/3","12":"","13":"5,500 - 7,500","14":"6,000","15":"80","16":"55 - 65","17":"55","18":"91 2/3","19":"1929","20":"","21":"1929","22":""},"8":{"c":"90","b":"100","a":"80"},"9":{"c":"good","b":"$7,000 singles","a":"Good"},"10":{"c":"good - none available","b":"$55 - 65","a":"Good"},"11":{"b":"12 to 15 houses","a":"Brick-detached-8,000"},"12":{"b":"Good","a":"Good"},"13":"Upward","14":"All business concentrated in one section. Low green.","15":{"1":"F. C. Devlin, Jr. Field Agent A. Lawson, Jr. - Field Agent-G.A. Fleming - Loan Service Repr.","2":"2/25/1937","3":""}}},"B2":{"ad_id":117,"name":null,"holc_grade":"B","sheets":1,"url":"//s3.amazonaws.com/holc/ads/OH/Dayton/1937/B2/{z}/{x}_{y}.png","areaDesc":{"1":{"1":"Van Buren Township - East of Oakwood","2":"B","3":"2"},"2":"High-level","3":"Restricted - good residential section - good schools and transportation.","4":"None","5":{"g":{"1":"Fast","2":""},"f":"None","e":"None","d":{"1":"None","2":""},"c":{"1":"None","2":""},"b":"2,400","a":"Middle Class"},"6":{"d":"good","c":"15 yrs","b":"Brick & frame","a":"Single family detached"},"7":{"1":"$7,000 - 9,000","2":"$8,000","3":"40 - 60","4":"50","5":"1933","6":"4,000 - 5,500","7":"4,750","8":"59.385%","9":"30 - 40","10":"35","11":"70","12":"1937","13":"5,000 - 7,000","14":"6,000","15":"75%","16":"40 - 55","17":"45","18":"90","19":"1929","20":"","21":"1929","22":""},"8":{"c":"90","b":"100","a":"20"},"9":{"c":"Fair","b":"Singles - $6,500","a":"Good"},"10":{"c":"Good","b":"$45","a":"Good"},"11":{"b":"20-22 houses","a":"Brick & Frame $7,000"},"12":{"b":"Ample","a":"Ample"},"13":"Good at best","14":"Southern portion outside city - no police protection township fire protection.","15":{"1":"F.C. Devlin, Jr. Field Agent, A. Lawson, Jr. Field Agent - C.A. Fleming, Loan Service Representative","2":"February 25, 1937","3":""}}},"C1":{"ad_id":117,"name":null,"holc_grade":"C","sheets":1,"url":"//s3.amazonaws.com/holc/ads/OH/Dayton/1937/C1/{z}/{x}_{y}.png","areaDesc":{"1":{"1":"Dayton","2":"C","3":"1"},"2":"High - level","3":"Good transportation; good schools; playgrounds; restricted to frame or better singles and double houses; all street improvements; churches.","4":"None.","5":{"g":{"1":"","2":"xxxxxx"},"f":"10%","e":"No","d":{"1":"No","2":""},"c":{"1":"None","2":""},"b":"1,500","a":"Better Class laborers - Clerks"},"6":{"d":"Fair","c":"15 yrs.","b":"Frame","a":"1-story & 2 story 5&6 rooms - mostly one family"},"7":{"1":"$3,000 - 7,000","2":"$6,000","3":"$35 - 45","4":"40","5":"1933","6":"2,500 - 3,500","7":"3,200","8":"53.3","9":"20 - 30","10":"25","11":"62.5","12":"1937","13":"3,500 - 5,000","14":"4,200","15":"70","16":"30 - 35","17":"35","18":"87.50%","19":"1929","20":"","21":"1929","22":""},"8":{"c":"90","b":"95","a":"75"},"9":{"c":"Fair","b":"$3,800","a":"Fair"},"10":{"c":"Good","b":"$34","a":"Good"},"11":{"b":"Fair 18 - 20","a":"1 family frame $4000"},"12":{"b":"Ample","a":"Ample"},"13":"Up","14":"Good transportation Very few \"Jerry built houses\" High Yellow.","15":{"1":"F.C. Devlin, Jr., Field Agent, A. Lawson, Jr., Field Agent, C.A. Fleming, Loan Service Representative","2":"March 1, 1937","3":""}}},"D2":{"ad_id":117,"name":null,"holc_grade":"D","sheets":1,"url":"//s3.amazonaws.com/holc/ads/OH/Dayton/1937/D2/{z}/{x}_{y}.png","areaDesc":{"1":{"1":"Dayton","2":"D","3":"2"},"2":"High-rolling","3":"None","4":"Entire area consists of shacks on rear of lots; no street improvements; no plat restrictions; inhabited by low class of white people; poor transportation.","5":{"g":{"1":"xxxxx","2":"xxxxx"},"f":"60%","e":"Lower class of white","d":{"1":"None","2":""},"c":{"1":"None","2":""},"b":"700","a":"Laborers"},"6":{"d":"Poor","c":"15 years","b":"Frame","a":"1 & 2 story singles detached and shacks"},"7":{"1":"1800 - 2000","2":"$2,000","3":"$13 - 18","4":"$15","5":"1933","6":"800 - 1000","7":"900","8":"45","9":"6 - 10","10":"8","11":"53.3","12":"1937","13":"1200 - 1800","14":"1400","15":"70","16":"8 - 12","17":"10","18":"66.6","19":"1929","20":"","21":"1929","22":""},"8":{"c":"75","b":"100","a":"30"},"9":{"c":"poor","b":"1 family $1500","a":"Poor"},"10":{"c":"poor","b":"1 family $10","a":"Poor"},"11":{"b":"","a":"none"},"12":{"b":"","a":"none"},"13":"Downward","14":"Low Red","15":{"1":"F.C. Devlin, Jr., Field Agent, A. Lawson Jr., Field Agent., C.A. Fleming, Loan Service Representative","2":"March 9, 1937","3":""}}},"B5":{"ad_id":117,"name":null,"holc_grade":"B","sheets":1,"url":"//s3.amazonaws.com/holc/ads/OH/Dayton/1937/B5/{z}/{x}_{y}.png","areaDesc":{"1":{"1":"Dayton, Beverly Hills, Brenner Plat.","2":"B","3":"5"},"2":"Rolling - high","3":"Desirable residential section - we'll restricted","4":"None","5":{"g":{"1":"","2":""},"f":"None","e":"None","d":{"1":"None","2":""},"c":{"1":"None","2":""},"b":"2,400","a":"Skilled mechanics, Jr. Executives and Railroad men"},"6":{"d":"Fair","c":"25 years","b":"Frame","a":"Singles - few doubles"},"7":{"1":"$6,500 - 8,500","2":"$7,000","3":"$45 - 55","4":"$50","5":"1933","6":"3,500 - 5,500","7":"3,500","8":"50","9":"25 - 35","10":"25","11":"50","12":"1937","13":"4,500 - 6,000","14":"5,200","15":"74.29%","16":"35 - 45","17":"40","18":"80","19":"1929","20":"","21":"1929","22":""},"8":{"c":"80","b":"100","a":"90"},"9":{"c":"Fair","b":"$5,000 singles","a":"Fair"},"10":{"c":"Good","b":"$40","a":"Good"},"11":{"b":"10 - 12 houses","a":"Frame $6,000"},"12":{"b":"ample","a":"ample"},"13":"Static","14":"An older residential section retaining good character and desirable inhabitants. Medium blue.","15":{"1":"F.C. Devlin - Jr., Field Agent, A. Lawson Jr., Field Agent - C.A. Fleming - Loan Service Representative","2":"February 25, 1937","3":""}}},"B6":{"ad_id":117,"name":null,"holc_grade":"B","sheets":1,"url":"//s3.amazonaws.com/holc/ads/OH/Dayton/1937/B6/{z}/{x}_{y}.png","areaDesc":{"1":{"1":"Dayton","2":"B","3":"6"},"2":"High level","3":"Fairly desirable","4":"Some jerry-built houses","5":{"g":{"1":"","2":""},"f":"None","e":"None","d":{"1":"None","2":""},"c":{"1":"None","2":""},"b":"2,000","a":"Mechanics - clerks"},"6":{"d":"Fair","c":"18 years","b":"Frame - some jerry built","a":"1 Family detached"},"7":{"1":"$5,000 - 6,500","2":"$5,500","3":"$35 - 45","4":"$40","5":"1933","6":"2,700 - 3,500","7":"2,750","8":"50%","9":"20 - 30","10":"20","11":"50","12":"1937","13":"4,500 - 5,500","14":"4,500","15":"81.80%","16":"30 - 35","17":"35","18":"87.50%","19":"1929","20":"","21":"1929","22":""},"8":{"c":"50","b":"100","a":"80"},"9":{"c":"Fair","b":"$4,000 singles","a":"Fair"},"10":{"c":"Good","b":"$35","a":"Good"},"11":{"b":"3 houses","a":"Frame $5,000"},"12":{"b":"ample","a":"ample"},"13":"Static to downward","14":"A very pale blue in desirability","15":{"1":"F.C. Devlin, Jr., Field Agent, A. Lawson, Jr., Field Agent, C.A. Fleming, Loan Service Representative.","2":"February 27, 1937","3":""}}},"D4":{"ad_id":117,"name":null,"holc_grade":"D","sheets":1,"url":"//s3.amazonaws.com/holc/ads/OH/Dayton/1937/D4/{z}/{x}_{y}.png","areaDesc":{"1":{"1":"Dayton","2":"D","3":"4"},"2":"Low","3":"Good transportation - Good schools","4":"Stockyards - packing houses and fertilizer plants adjacent to area.","5":{"g":{"1":"xxxxx","2":"xxxxx"},"f":"80%","e":"Negro","d":{"1":"Yes","2":"80"},"c":{"1":"Hungarian/Polish","2":"26"},"b":"700","a":"Laborer"},"6":{"d":"Poor","c":"30 years","b":"Frame","a":"1 family detached and shacks."},"7":{"1":"","2":"$1,500","3":"","4":"$15","5":"1933","6":"","7":"600","8":"40","9":"","10":"6","11":"40","12":"1937","13":"","14":"800","15":"53.30%","16":"","17":"8","18":"53.3","19":"1929","20":"","21":"1929","22":""},"8":{"c":"40","b":"100","a":"60"},"9":{"c":"","b":"","a":"None"},"10":{"c":"fair","b":"1 family detached","a":"Fair"},"11":{"b":"","a":"None"},"12":{"b":"","a":"None"},"13":"Downward","14":"Trend towards industrial - Low red.","15":{"1":"F.C. Devlin- Jr., Field Agent A. Lawson, Jr., Field Agent, C.A. Fleming, Loan Service Representative","2":"March 9, 1937","3":""}}},"D7":{"ad_id":117,"name":null,"holc_grade":"D","sheets":1,"url":"//s3.amazonaws.com/holc/ads/OH/Dayton/1937/D7/{z}/{x}_{y}.png","areaDesc":{"1":{"1":"Dayton","2":"D","3":"7"},"2":"Low","3":"Good schools, good transportation","4":"Bad odors from industrial plants; old section.","5":{"g":{"1":"xxxxx","2":"xxxxx"},"f":"50%","e":"Foreign born","d":{"1":"Yes","2":"10"},"c":{"1":"Polish-Hungarian","2":"90"},"b":"1200","a":"Laborers"},"6":{"d":"Fair","c":"40 yrs.","b":"Frame","a":"1 & 2 family detached"},"7":{"1":"","2":"2500","3":"","4":"25","5":"1933","6":"","7":"1000","8":"40","9":"","10":"12","11":"48","12":"1937","13":"","14":"1800","15":"72","16":"","17":"18","18":"72","19":"","20":"1929","21":"","22":"1929"},"8":{"c":"80","b":"98","a":"80"},"9":{"c":"","b":"","a":"None"},"10":{"c":"Fair","b":"Single family detached","a":"Fair"},"11":{"b":"","a":"None"},"12":{"b":"Limited","a":"Limited"},"13":"Downward","14":"Low Red.","15":{"1":"F.C. Devlin, Jr., Field Agent, A. Lawson, Jr., Field Agent, C.A. Fleming - Loan Service Representative","2":"March 10, 1937","3":""}}},"C9":{"ad_id":117,"name":null,"holc_grade":"C","sheets":1,"url":"//s3.amazonaws.com/holc/ads/OH/Dayton/1937/C9/{z}/{x}_{y}.png","areaDesc":{"1":{"1":"Dayton","2":"C","3":"9"},"2":"Level","3":"Good playgrounds; transportation; schools.","4":"None","5":{"g":{"1":"","2":"xxxxx"},"f":"15%","e":"Foreign","d":{"1":"No","2":""},"c":{"1":"Polish-Hungarian","2":"80"},"b":"1,500","a":"Laborers-Mechanics"},"6":{"d":"Good","c":"20 years","b":"Frame","a":"Single detached 5 & 6 room"},"7":{"1":"$4,500 - 5,500","2":"$5,000","3":"$35 - 45","4":"$40","5":"1933","6":"2,000 - 3,000","7":"2,500","8":"50","9":"20 - 30","10":"25","11":"62.50%","12":"1937","13":"$3,500 - 4,000","14":"3,800","15":"76%","16":"30 - 40","17":"35","18":"87.50%","19":"1929","20":"","21":"1929","22":""},"8":{"c":"80","b":"100","a":"80"},"9":{"c":"","b":"","a":"None"},"10":{"c":"Good","b":"$35 single","a":"Good single family"},"11":{"b":"12 - 15","a":"Single family detached 5 room $4,000"},"12":{"b":"Limited","a":"Limited"},"13":"Upward, better class foreign","14":"Low yellow.","15":{"1":"F.C. Devlin, Jr. Field Agent, A. Lawson, Jr. Field Agent, C.A. Fleming, Loan Service Representative","2":"March 8, 1937","3":""}}},"B8":{"ad_id":117,"name":null,"holc_grade":"B","sheets":1,"url":"//s3.amazonaws.com/holc/ads/OH/Dayton/1937/B8/{z}/{x}_{y}.png","areaDesc":{"1":{"1":"Dayton","2":"B","3":"8"},"2":"Rolling - high","3":"Well laid out section of desirably larger houses.","4":"None","5":{"g":{"1":"slowly","2":""},"f":"None","e":"None","d":{"1":"None","2":""},"c":{"1":"None","2":""},"b":"3,500","a":"Executives & Professional men"},"6":{"d":"Good to excellent","c":"15 - 20 years","b":"Brick & Frame","a":"one family detached"},"7":{"1":"$8,000 - 10,000","2":"$9,000","3":"$65 - 75","4":"$70","5":"1933","6":"4,500 - 6,000","7":"4,500","8":"50%","9":"30 - 40","10":"35","11":"50%","12":"1937","13":"7,000 - 9,000","14":"8,000","15":"88.80%","16":"55 - 65","17":"60","18":"85.70%","19":"1929","20":"","21":"1929","22":""},"8":{"c":"85","b":"100","a":"70"},"9":{"c":"Good","b":"$8,000 - single","a":"Fair"},"10":{"c":"Good","b":"$60","a":"Good"},"11":{"b":"15 - 20 houses $9,000","a":"Frame & Brick"},"12":{"b":"Ample","a":"Ample"},"13":"Upward","14":"High Blue","15":{"1":"F.C. Devlin, Jr., Field Agent, A. Lawson Jr., Field Agent, C.A. Fleming - Loan Service Representative","2":"March 1, 1937","3":""}}},"B9":{"ad_id":117,"name":null,"holc_grade":"B","sheets":1,"url":"//s3.amazonaws.com/holc/ads/OH/Dayton/1937/B9/{z}/{x}_{y}.png","areaDesc":{"1":{"1":"Dayton","2":"B","3":"9"},"2":"Rolling","3":"Continues as well restricted residential section","4":"None","5":{"g":{"1":"Slowly","2":""},"f":"None","e":"None","d":{"1":"No","2":""},"c":{"1":"None","2":""},"b":"$4,000 & Over","a":"Executive - Professional Men"},"6":{"d":"Good","c":"25 years","b":"Brick","a":"1 family detached"},"7":{"1":"$10,000 - 12,000","2":"$11,000","3":"","4":"","5":"1933","6":"5,500 - 6,500","7":"6,000","8":"54.50%","9":"No Rentals","10":"","11":"","12":"","13":"8,000 - 10,000","14":"9,000","15":"81.80%","16":"","17":"","18":"","19":"1929","20":"","21":"1929","22":""},"8":{"c":"100","b":"100","a":"80"},"9":{"c":"Fair","b":"$9,000 Singles","a":"Good"},"10":{"c":"","b":"No rentals","a":""},"11":{"b":"18 - 20 Houses - 12,000","a":"Brick"},"12":{"b":"Ample","a":"Ample"},"13":"Upward","14":"High Blue","15":{"1":"F.C. Devlin, Jr., Field Agent, A. Lawson, Jr., Field Agent, C.A. Fleming - Loan Service Representative","2":"March 3, 1937","3":""}}}}